mauve_gpu/__init__.py
mauve_gpu/core.py
mauve_gpu-0.3.9.dist-info/licenses/LICENSE
mauve_gpu-0.3.9.dist-info/METADATA
mauve_gpu-0.3.9.dist-info/WHEEL
mauve_gpu-0.3.9.dist-info/top_level.txt
mauve_gpu-0.3.9.dist-info/RECORD
