Metadata-Version: 2.4
Name: mauve-gpu
Version: 0.3.9
Summary: A GPU-accelerated (cuML) implementation of the MAUVE score for comparing distributions.
Author-email: Daniel Wood <daniel@wolber-wood.com>
License: 
Project-URL: Homepage, https://github.com/danielwolber-wood/mauve-gpu
Project-URL: Bug Tracker, https://github.com/danielwolber-wood/mauve-gpu/issues
Classifier: Programming Language :: Python :: 3
Classifier: License :: OSI Approved :: Apache Software License
Classifier: Operating System :: OS Independent
Classifier: Intended Audience :: Science/Research
Classifier: Topic :: Scientific/Engineering :: Artificial Intelligence
Requires-Python: >=3.8
License-File: LICENSE
Requires-Dist: numpy<2.3
Provides-Extra: dev
Requires-Dist: pytest; extra == "dev"
Provides-Extra: examples
Requires-Dist: pandas; extra == "examples"
Requires-Dist: sentence-transformers; extra == "examples"
Dynamic: license-file
